umfpayservice/__init__.py
umfpayservice/api_requestor.py
umfpayservice/common.py
umfpayservice/error.py
umfpayservice/http_client.py
umfpayservice/regex_check.py
umfpayservice/resource.py
umfpayservice/sign.py
umfpayservice/umfservice.py
umfpayservice/util.py
umfpayservice/version.py
umfpayservice-1.3.2.dist-info/DESCRIPTION.rst
umfpayservice-1.3.2.dist-info/METADATA
umfpayservice-1.3.2.dist-info/RECORD
umfpayservice-1.3.2.dist-info/WHEEL
umfpayservice-1.3.2.dist-info/metadata.json
umfpayservice-1.3.2.dist-info/top_level.txt
