Metadata-Version: 2.0
Name: umfpayservice
Version: 1.3.2
Summary: umfpayservice python bindings
Home-page: https://xy.umfintech.com/spEnterprise/
Author: Umf
Author-email: hanpeidong@umpay.com
License: UNKNOWN
Platform: UNKNOWN
Classifier: Intended Audience :: Developers
Classifier: License :: OSI Approved :: MIT License
Classifier: Operating System :: OS Independent
Classifier: Programming Language :: Python
Classifier: Programming Language :: Python :: 2
Classifier: Programming Language :: Python :: 2.6
Classifier: Programming Language :: Python :: 2.7
Classifier: Programming Language :: Python :: 3
Classifier: Programming Language :: Python :: 3.2
Classifier: Programming Language :: Python :: 3.3
Classifier: Programming Language :: Python :: 3.4
Requires-Dist: requests (>=0.8.8)
Requires-Dist: pycrypto (>=2.6.1)
Requires-Dist: beautifulsoup4
